rasa_alice/__init__.py
rasa_alice/channel.py
rasa_alice/types.py
rasa_alice-0.1.1.dist-info/LICENSE.txt
rasa_alice-0.1.1.dist-info/METADATA
rasa_alice-0.1.1.dist-info/WHEEL
rasa_alice-0.1.1.dist-info/top_level.txt
rasa_alice-0.1.1.dist-info/RECORD
