Metadata-Version: 2.1
Name: rasa-alice
Version: 0.1.1
Summary: Rasa Connector for Yandex Dialogs.
Home-page: https://github.com/r-m-n/rasa-alice
License: MIT
Platform: UNKNOWN
Requires-Python: >=3.6
Requires-Dist: rasa (>=1.5.0)
Requires-Dist: pydantic (>=1.1.1)
Provides-Extra: dev
Requires-Dist: pytest ; extra == 'dev'
Requires-Dist: flake8 ; extra == 'dev'
Requires-Dist: tox ; extra == 'dev'
